<annotation>
	<folder>Images</folder>
	<filename>1553233009-construction-workers-sydney-960x540.jpg</filename>
	<path>/Users/ricmagno/Dropbox/WorkingBox/SoftwareDev/Coco_ssd_mobilenet/Dataset/Images/1553233009-construction-workers-sydney-960x540.jpg</path>
	<source>
		<database>Unknown</database>
	</source>
	<size>
		<width>960</width>
		<height>540</height>
		<depth>3</depth>
	</size>
	<segmented>0</segmented>
	<object>
		<name>hard hat</name>
		<pose>Unspecified</pose>
		<truncated>0</truncated>
		<difficult>0</difficult>
		<bndbox>
			<xmin>300</xmin>
			<ymin>127</ymin>
			<xmax>363</xmax>
			<ymax>171</ymax>
		</bndbox>
	</object>
	<object>
		<name>hard hat</name>
		<pose>Unspecified</pose>
		<truncated>0</truncated>
		<difficult>0</difficult>
		<bndbox>
			<xmin>395</xmin>
			<ymin>94</ymin>
			<xmax>454</xmax>
			<ymax>133</ymax>
		</bndbox>
	</object>
	<object>
		<name>hard hat</name>
		<pose>Unspecified</pose>
		<truncated>0</truncated>
		<difficult>0</difficult>
		<bndbox>
			<xmin>452</xmin>
			<ymin>135</ymin>
			<xmax>511</xmax>
			<ymax>175</ymax>
		</bndbox>
	</object>
	<object>
		<name>hard hat</name>
		<pose>Unspecified</pose>
		<truncated>0</truncated>
		<difficult>0</difficult>
		<bndbox>
			<xmin>541</xmin>
			<ymin>130</ymin>
			<xmax>610</xmax>
			<ymax>174</ymax>
		</bndbox>
	</object>
	<object>
		<name>hard hat</name>
		<pose>Unspecified</pose>
		<truncated>0</truncated>
		<difficult>0</difficult>
		<bndbox>
			<xmin>622</xmin>
			<ymin>111</ymin>
			<xmax>677</xmax>
			<ymax>156</ymax>
		</bndbox>
	</object>
	<object>
		<name>hard hat</name>
		<pose>Unspecified</pose>
		<truncated>0</truncated>
		<difficult>0</difficult>
		<bndbox>
			<xmin>806</xmin>
			<ymin>129</ymin>
			<xmax>865</xmax>
			<ymax>172</ymax>
		</bndbox>
	</object>
	<object>
		<name>high-vis</name>
		<pose>Unspecified</pose>
		<truncated>0</truncated>
		<difficult>0</difficult>
		<bndbox>
			<xmin>254</xmin>
			<ymin>187</ymin>
			<xmax>404</xmax>
			<ymax>340</ymax>
		</bndbox>
	</object>
	<object>
		<name>high-vis</name>
		<pose>Unspecified</pose>
		<truncated>0</truncated>
		<difficult>0</difficult>
		<bndbox>
			<xmin>530</xmin>
			<ymin>194</ymin>
			<xmax>665</xmax>
			<ymax>354</ymax>
		</bndbox>
	</object>
</annotation>
